melkor/__init__.py
melkor/__main__.py
melkor/customTypes.py
melkor/engine.py
melkor/settings.py
melkor/tester.py
melkor/utils.py
melkor/output/junit.py
melkor-1.0.6.dist-info/METADATA
melkor-1.0.6.dist-info/WHEEL
melkor-1.0.6.dist-info/entry_points.txt
melkor-1.0.6.dist-info/top_level.txt
melkor-1.0.6.dist-info/RECORD
