Metadata-Version: 2.1
Name: melkor
Version: 1.0.6
Summary: A python testing library
Author-email: Antoine Buirey <antoine.buirey@gmail.com>
Classifier: Programming Language :: Python :: 3
Classifier: License :: OSI Approved :: MIT License
Classifier: Operating System :: OS Independent
Requires-Python: >=3.11
Requires-Dist: gamuLogger >=3.0.0
Requires-Dist: json5 >=0.9.25
